{
  "kind": "collectionType",
  "collectionName": "dealers",
  "info": {
    "singularName": "dealer",
    "pluralName": "dealers",
    "displayName": "Dealer",
    "description": ""
  },
  "options": {
    "draftAndPublish": true
  },
  "pluginOptions": {},
  "attributes": {
    "name": {
      "type": "string",
      "required": true,
      "unique": true
    },
    "address": {
      "type": "text"
    },
    "phone": {
      "type": "string"
    },
    "map_link": {
      "type": "string"
    },
    "latitude": {
      "type": "string"
    },
    "longitude": {
      "type": "string"
    },
    "postal_code": {
      "type": "string"
    },
    "product_line": {
      "type": "relation",
      "relation": "oneToOne",
      "target": "api::product-line.product-line"
    },
    "product_category": {
      "type": "relation",
      "relation": "oneToOne",
      "target": "api::product-category.product-category"
    },
    "brand": {
      "type": "relation",
      "relation": "oneToOne",
      "target": "api::brand.brand"
    }
  }
}
